git_app_version/__init__.py
git_app_version/__main__.py
git_app_version/_version.py
git_app_version/dumper.py
git_app_version/githandler.py
git_app_version/helper/__init__.py
git_app_version/helper/date.py
git_app_version/helper/tools.py
test_helpers/__init__.py
test_helpers/git_utils.py
git_app_version-1.0.2.dist-info/LICENSE
git_app_version-1.0.2.dist-info/METADATA
git_app_version-1.0.2.dist-info/WHEEL
git_app_version-1.0.2.dist-info/entry_points.txt
git_app_version-1.0.2.dist-info/top_level.txt
git_app_version-1.0.2.dist-info/RECORD
