Metadata-Version: 2.1
Name: git-app-version
Version: 1.0.2
Summary: CLI tool to get Git commit informations and store them in a config file
Home-page: https://github.com/csanquer/git-app-version
Author: Charles Sanquer
Author-email: charles.sanquer.pro@gmail.com
License: GPLv3
Keywords: git version commit deploy tools
Platform: UNKNOWN
Classifier: Development Status :: 4 - Beta
Classifier: Intended Audience :: Developers
Classifier: Topic :: Software Development :: Build Tools
Classifier: License :: OSI Approved :: GNU General Public License v3 or later (GPLv3+)
Classifier: Programming Language :: Python :: 2.7
Classifier: Programming Language :: Python :: 3.4
Classifier: Programming Language :: Python :: 3.5
Classifier: Programming Language :: Python :: 3.6
Classifier: Programming Language :: Python :: 3.7
Requires-Dist: future
Requires-Dist: backports.csv
Requires-Dist: configparser (>=3.5.0)
Requires-Dist: iso8601
Requires-Dist: pyyaml
Requires-Dist: pytz
Requires-Dist: xmltodict
Requires-Dist: tzlocal
Requires-Dist: gitpython
Requires-Dist: tabulate (>=0.7.0)
Requires-Dist: click (>=6.0)
Provides-Extra: dev
Requires-Dist: versioneer ; extra == 'dev'
Requires-Dist: check-manifest ; extra == 'dev'
Requires-Dist: pyinstaller (>=3.2pylint) ; extra == 'dev'
Requires-Dist: pycodestyle ; extra == 'dev'
Requires-Dist: yapf ; extra == 'dev'
Requires-Dist: flake8 ; extra == 'dev'
Requires-Dist: isort ; extra == 'dev'
Provides-Extra: test
Requires-Dist: pytest-cov ; extra == 'test'
Requires-Dist: pytest (>=3.0) ; extra == 'test'
Requires-Dist: mock ; extra == 'test'
Requires-Dist: tox ; extra == 'test'
